pysheets/__init__.py
pysheets/spreadsheet.py
pysheets/tools.py
PySheets-1.0.3.dist-info/METADATA
PySheets-1.0.3.dist-info/WHEEL
PySheets-1.0.3.dist-info/top_level.txt
PySheets-1.0.3.dist-info/RECORD
