Metadata-Version: 2.1
Name: PySheets
Version: 1.0.3
Summary: An interactive way to interact with spreadsheets in python. Supports CSV importing and exporting.
Home-page: UNKNOWN
Author: UNKNOWN
Author-email: UNKNOWN
License: UNKNOWN
Platform: UNKNOWN
